{
  "fetched_at": "2026-05-13T17:13:18+00:00",
  "count": 60,
  "tiles": [
    {
      "kind": "news",
      "title": "China encourages lithium value addition partnership with Zimbabwe for industrial growth",
      "link": "https://mutapatimes.com/news/2026-05-13-china-encourages-lithium-value-addition-partnership-with-zim-e8a18a",
      "image": "https://www.mutapatimes.com/img/cards/news/fee5b49f3b22.png",
      "pubDate": "2026-05-13T16:04:55+00:00",
      "category": "Business"
    },
    {
      "kind": "news",
      "title": "Zimbabwe seeks up to US$200 million in UAE investment for key sectors",
      "link": "https://mutapatimes.com/articles/2026-05-13-zimbabwe-seeks-up-to-us200-million-in-uae-investment-for-key",
      "image": "https://www.mutapatimes.com/img/cards/news/eca29b490641.png",
      "pubDate": "2026-05-13T15:02:17+00:00",
      "category": "Business"
    },
    {
      "kind": "news",
      "title": "Zimbabwe seeks up to US$200 million in UAE investment for key sectors",
      "link": "https://mutapatimes.com/news/2026-05-13-zimbabwe-seeks-up-to-us-200-million-in-uae-investment-for-ke-929f7b",
      "image": "https://www.mutapatimes.com/img/cards/news/95d6cbf23bc3.png",
      "pubDate": "2026-05-13T15:02:17+00:00",
      "category": "Business"
    },
    {
      "kind": "news",
      "title": "Zimbabwe courts US$200 million UAE investments",
      "link": "https://mutapatimes.com/news/2026-05-13-zimbabwe-courts-us-200-million-uae-investments-39e5a6",
      "image": "https://www.mutapatimes.com/img/cards/news/c8893e422843.png",
      "pubDate": "2026-05-13T12:45:05+00:00",
      "category": "Business"
    },
    {
      "kind": "news",
      "title": "Minister Soda, Amb Shoniwa engage Zimbabwe diasporans in China",
      "link": "https://mutapatimes.com/news/2026-05-13-minister-soda-amb-shoniwa-engage-zimbabwe-diasporans-in-chin-749bca",
      "image": "https://www.mutapatimes.com/img/cards/news/0bb922c1ca84.png",
      "pubDate": "2026-05-13T12:35:37+00:00",
      "category": "Business"
    },
    {
      "kind": "news",
      "title": "Shumba Maasai Brings Zimbabwean Cultural Interventions to Venice Biennale with Procession Across Historic Campos",
      "link": "https://mutapatimes.com/articles/2026-05-13-shumba-maasai-venice-biennale-zimbabwean-cultural-interventions",
      "image": "https://www.mutapatimes.com/img/cards/news/bc035a047c91.png",
      "pubDate": "2026-05-13T12:00:00+00:00",
      "category": "Culture"
    },
    {
      "kind": "news",
      "title": "Shumba Maasai Brings Zimbabwean Cultural Interventions to Venice Biennale with Procession Across Historic Campos",
      "link": "https://mutapatimes.com/news/2026-05-13-shumba-maasai-brings-zimbabwean-cultural-interventions-to-ve-09b0ab",
      "image": "https://www.mutapatimes.com/img/cards/news/7266d54dcfdc.png",
      "pubDate": "2026-05-13T12:00:00+00:00",
      "category": "News"
    },
    {
      "kind": "news",
      "title": "Zimbabwe Embassy Islamabad Hosts 7th IYDS",
      "link": "https://mutapatimes.com/news/2026-05-13-zimbabwe-embassy-islamabad-hosts-7th-iyds-7bd31a",
      "image": "https://www.mutapatimes.com/img/cards/news/28c05d2d9b0e.png",
      "pubDate": "2026-05-13T09:55:50+00:00",
      "category": "Business"
    },
    {
      "kind": "news",
      "title": "Zimbabwe, Botswana vaccinate 72,000 cattle against FMD as South Africa battles outbreak control challenges",
      "link": "https://mutapatimes.com/news/2026-05-13-zimbabwe-botswana-vaccinate-72-000-cattle-against-fmd-as-sou-8d6b2c",
      "image": "https://www.mutapatimes.com/img/cards/news/d8e132d93e01.png",
      "pubDate": "2026-05-13T09:55:24+00:00",
      "category": "Science"
    },
    {
      "kind": "news",
      "title": "Zimbabwe, Botswana vaccinate 72,000 cattle against FMD as South Africa battles outbreak control challenges",
      "link": "https://mutapatimes.com/articles/2026-05-13-zimbabwe-botswana-vaccinate-72000-cattle-against-fmd-as-sout",
      "image": "https://www.mutapatimes.com/img/cards/news/52b4f02c4332.png",
      "pubDate": "2026-05-13T09:45:28+00:00",
      "category": "Tech"
    },
    {
      "kind": "news",
      "title": "Fastjet renews IOSA certification",
      "link": "https://mutapatimes.com/articles/2026-05-13-fastjet-renews-iosa-certification",
      "image": "https://www.mutapatimes.com/img/cards/news/a69e3d94b888.png",
      "pubDate": "2026-05-13T09:41:55+00:00",
      "category": "Culture"
    },
    {
      "kind": "news",
      "title": "Fastjet renews IOSA certification",
      "link": "https://mutapatimes.com/news/2026-05-13-fastjet-renews-iosa-certification-29ef52",
      "image": "https://www.mutapatimes.com/img/cards/news/a36d711eac97.png",
      "pubDate": "2026-05-13T09:41:55+00:00",
      "category": "Entertainment"
    },
    {
      "kind": "news",
      "title": "Former Minister Mzembi acquitted of abuse of office charges",
      "link": "https://mutapatimes.com/news/2026-05-13-former-minister-mzembi-acquitted-of-abuse-of-office-charges-a648e2",
      "image": "https://www.mutapatimes.com/img/cards/news/cb2c549f5c95.png",
      "pubDate": "2026-05-13T08:49:19+00:00",
      "category": "Entertainment"
    },
    {
      "kind": "news",
      "title": "Fidelity Gold Refinery intensifies drive to formalise small-scale gold mining sector, plug leakages",
      "link": "https://mutapatimes.com/articles/2026-05-13-fidelity-gold-refinery-intensifies-drive-to-formalise-small",
      "image": "https://www.mutapatimes.com/img/cards/news/eadba53f4e24.png",
      "pubDate": "2026-05-13T07:45:19+00:00",
      "category": "Business"
    },
    {
      "kind": "news",
      "title": "Fidelity Gold Refinery intensifies drive to formalise small-scale gold mining sector, plug leakages",
      "link": "https://mutapatimes.com/news/2026-05-13-fidelity-gold-refinery-intensifies-drive-to-formalise-small-404816",
      "image": "https://www.mutapatimes.com/img/cards/news/553f57dd0f9f.png",
      "pubDate": "2026-05-13T07:45:19+00:00",
      "category": "Business"
    },
    {
      "kind": "news",
      "title": "Family of collapsed mine victim speak out",
      "link": "https://mutapatimes.com/articles/2026-05-13-family-of-collapsed-mine-victim-speak-out",
      "image": "https://www.mutapatimes.com/img/cards/news/7322d4ed8ce4.png",
      "pubDate": "2026-05-13T07:20:58+00:00",
      "category": "Business"
    },
    {
      "kind": "news",
      "title": "Family of collapsed mine victim speak out",
      "link": "https://mutapatimes.com/news/2026-05-13-family-of-collapsed-mine-victim-speak-out-7a105a",
      "image": "https://www.mutapatimes.com/img/cards/news/8d4b22b741ce.png",
      "pubDate": "2026-05-13T07:20:58+00:00",
      "category": "Business"
    },
    {
      "kind": "news",
      "title": "‘Even captured courts will not allow the Constitution Amendment Bill to escape a referendum’ – Madhuku",
      "link": "https://mutapatimes.com/news/2026-05-13-even-captured-courts-will-not-allow-the-constitution-amendme-ad55c1",
      "image": "https://www.mutapatimes.com/img/cards/news/58915e2685ab.png",
      "pubDate": "2026-05-13T05:34:55+00:00",
      "category": "Entertainment"
    },
    {
      "kind": "news",
      "title": "Mnangagwa completes long-delayed Sibanda Zanu-PF politburo appointment",
      "link": "https://mutapatimes.com/news/2026-05-13-mnangagwa-completes-long-delayed-sibanda-zanu-pf-politburo-a-9857fe",
      "image": "https://www.mutapatimes.com/img/cards/news/f35db344755d.png",
      "pubDate": "2026-05-13T05:11:09+00:00",
      "category": "News"
    },
    {
      "kind": "news",
      "title": "Police officer & Minister Motsoaledi’s cars kill foreign Couple: Zimbabwean family wiped out in 2 separate accidents along N1 Highway",
      "link": "https://mutapatimes.com/news/2026-05-13-police-officer-minister-motsoaledi-s-cars-kill-foreign-coupl-c3db73",
      "image": "https://www.mutapatimes.com/img/cards/news/2954b910206e.png",
      "pubDate": "2026-05-13T04:50:25+00:00",
      "category": "News"
    },
    {
      "kind": "news",
      "title": "The price of Chivayo’s Fortuner: Why Zimpapers drew a line in the sand",
      "link": "https://mutapatimes.com/articles/2026-05-13-the-price-of-chivayos-fortuner-why-zimpapers-drew-a-line-in",
      "image": "https://www.mutapatimes.com/img/cards/news/eaa0da87fd02.png",
      "pubDate": "2026-05-13T04:03:39+00:00",
      "category": "Business"
    },
    {
      "kind": "news",
      "title": "The price of Chivayo’s Fortuner: Why Zimpapers drew a line in the sand",
      "link": "https://mutapatimes.com/news/2026-05-13-the-price-of-chivayo-s-fortuner-why-zimpapers-drew-a-line-in-8a2301",
      "image": "https://www.mutapatimes.com/img/cards/news/68a54d943f89.png",
      "pubDate": "2026-05-13T04:03:39+00:00",
      "category": "News"
    },
    {
      "kind": "news",
      "title": "CZI tells private sector to leverage Zim’s trade pacts",
      "link": "https://mutapatimes.com/articles/2026-05-13-czi-tells-private-sector-to-leverage-zims-trade-pacts",
      "image": "https://www.mutapatimes.com/img/cards/news/a19205569364.png",
      "pubDate": "2026-05-13T03:50:05+00:00",
      "category": "Business"
    },
    {
      "kind": "news",
      "title": "GMB pays wheat farmers US$4m to clear 2025 debt",
      "link": "https://mutapatimes.com/articles/2026-05-13-gmb-pays-wheat-farmers-us4m-to-clear-2025-debt",
      "image": "https://www.mutapatimes.com/img/cards/news/cccf545e2358.png",
      "pubDate": "2026-05-13T03:48:55+00:00",
      "category": "Business"
    },
    {
      "kind": "news",
      "title": "Mutapa Gold Resources seeks US$250m to extend mine life",
      "link": "https://mutapatimes.com/articles/2026-05-13-mutapa-gold-resources-seeks-us250m-to-extend-mine-life",
      "image": "https://www.mutapatimes.com/img/cards/news/9cc4bb78e1fa.png",
      "pubDate": "2026-05-13T03:48:25+00:00",
      "category": "Business"
    },
    {
      "kind": "news",
      "title": "Zimpapers orders staff to return Chivayo cash gifts, gives presenter vehicle ultimatum",
      "link": "https://mutapatimes.com/articles/2026-05-13-zimpapers-orders-staff-to-return-chivayo-cash-gifts-gives-pr",
      "image": "https://www.mutapatimes.com/img/cards/news/cd65e45a3302.png",
      "pubDate": "2026-05-13T00:30:46+00:00",
      "category": "Business"
    },
    {
      "kind": "news",
      "title": "Zimpapers orders staff to return Chivayo cash gifts, gives presenter vehicle ultimatum",
      "link": "https://mutapatimes.com/news/2026-05-13-zimpapers-orders-staff-to-return-chivayo-cash-gifts-gives-pr-96977d",
      "image": "https://www.mutapatimes.com/img/cards/news/5ac0c270c985.png",
      "pubDate": "2026-05-13T00:30:46+00:00",
      "category": "News"
    },
    {
      "kind": "news",
      "title": "600MW solar plant on cards",
      "link": "https://mutapatimes.com/articles/2026-05-12-600mw-solar-plant-on-cards",
      "image": "https://www.mutapatimes.com/img/cards/news/e1b14e87dcbd.png",
      "pubDate": "2026-05-12T23:58:00+00:00",
      "category": "Business"
    },
    {
      "kind": "news",
      "title": "Digital tools help curb stillbirth rates",
      "link": "https://mutapatimes.com/articles/2026-05-12-digital-tools-help-curb-stillbirth-rates",
      "image": "https://www.mutapatimes.com/img/cards/news/a7625bb8171d.png",
      "pubDate": "2026-05-12T23:56:00+00:00",
      "category": "Tech"
    },
    {
      "kind": "news",
      "title": "Freight costs threaten Zimbabwe farmers' jobs due to Iran war",
      "link": "https://mutapatimes.com/articles/2026-05-12-freight-costs-threaten-zimbabwe-farmers-jobs-due-to-iran-war",
      "image": "https://www.mutapatimes.com/img/cards/news/c66e82c358df.png",
      "pubDate": "2026-05-12T23:47:19+00:00",
      "category": "Business"
    },
    {
      "kind": "news",
      "title": "Zimbabwe to review lithium export quotas next year as producers set up processing plants",
      "link": "https://mutapatimes.com/articles/2026-05-12-zimbabwe-to-review-lithium-export-quotas-next-year-as-produc",
      "image": "https://www.mutapatimes.com/img/cards/news/046de12b3405.png",
      "pubDate": "2026-05-12T23:39:27+00:00",
      "category": "Business"
    },
    {
      "kind": "news",
      "title": "Zimbabwe to review lithium export quotas next year as producers set up processing plants",
      "link": "https://mutapatimes.com/news/2026-05-12-zimbabwe-to-review-lithium-export-quotas-next-year-as-produc-ec359f",
      "image": "https://www.mutapatimes.com/img/cards/news/28d008f016eb.png",
      "pubDate": "2026-05-12T23:39:27+00:00",
      "category": "News"
    },
    {
      "kind": "news",
      "title": "Freight costs threaten Zimbabwe farmers’ livelihoods as Iran war disrupts exports",
      "link": "https://mutapatimes.com/articles/2026-05-12-freight-costs-threaten-zimbabwe-farmers-livelihoods-as-iran",
      "image": "https://www.mutapatimes.com/img/cards/news/3e42f3b135ca.png",
      "pubDate": "2026-05-12T23:10:45+00:00",
      "category": "Business"
    },
    {
      "kind": "news",
      "title": "Who is funding anti-migrant protests in SA? – Zimbabwean international relations expert urges probe into organisers",
      "link": "https://mutapatimes.com/news/2026-05-12-who-is-funding-anti-migrant-protests-in-sa-zimbabwean-intern-c352e3",
      "image": "https://www.mutapatimes.com/img/cards/news/89a3a29caccd.png",
      "pubDate": "2026-05-12T23:07:27+00:00",
      "category": "News"
    },
    {
      "kind": "news",
      "title": "Tourism boost as Zimbabwe hosts Africa Skills Week",
      "link": "https://mutapatimes.com/articles/2026-05-12-tourism-boost-as-zimbabwe-hosts-africa-skills-week",
      "image": "https://www.mutapatimes.com/img/cards/news/fc528a6ace90.png",
      "pubDate": "2026-05-12T23:00:53+00:00",
      "category": "Business"
    },
    {
      "kind": "news",
      "title": "Tourism boost as Zimbabwe hosts Africa Skills Week",
      "link": "https://mutapatimes.com/news/2026-05-12-tourism-boost-as-zimbabwe-hosts-africa-skills-week-f3c9a1",
      "image": "https://www.mutapatimes.com/img/cards/news/22c0770d06e4.png",
      "pubDate": "2026-05-12T23:00:53+00:00",
      "category": "News"
    },
    {
      "kind": "news",
      "title": "Police hunt drug kingpins linked to armed robberies",
      "link": "https://mutapatimes.com/news/2026-05-12-police-hunt-drug-kingpins-linked-to-armed-robberies-4e5e4f",
      "image": "https://www.mutapatimes.com/img/cards/news/f28a8b26cc73.png",
      "pubDate": "2026-05-12T23:00:47+00:00",
      "category": "News"
    },
    {
      "kind": "news",
      "title": "Millennium Heights apartments sell out fast as demand surges",
      "link": "https://mutapatimes.com/articles/2026-05-12-millennium-heights-apartments-sell-out-fast-as-demand-surges",
      "image": "https://www.mutapatimes.com/img/cards/news/4c6ca5692fd7.png",
      "pubDate": "2026-05-12T23:00:18+00:00",
      "category": "Business"
    },
    {
      "kind": "news",
      "title": "Millennium Heights apartments sell out fast as demand surges",
      "link": "https://mutapatimes.com/news/2026-05-12-millennium-heights-apartments-sell-out-fast-as-demand-surges-ddf831",
      "image": "https://www.mutapatimes.com/img/cards/news/3df5c3418722.png",
      "pubDate": "2026-05-12T23:00:18+00:00",
      "category": "News"
    },
    {
      "kind": "news",
      "title": "Zimbabwe moves to accelerate SEZ roll-out inspired by China model",
      "link": "https://mutapatimes.com/articles/2026-05-12-zimbabwe-moves-to-accelerate-sez-roll-out-inspired-by-china",
      "image": "https://www.mutapatimes.com/img/cards/news/e91306a1990c.png",
      "pubDate": "2026-05-12T22:27:30+00:00",
      "category": "Policy"
    },
    {
      "kind": "news",
      "title": "International Nursing Day: Zimbabwe salutes its nurses",
      "link": "https://mutapatimes.com/articles/2026-05-12-international-nursing-day-zimbabwe-salutes-its-nurses",
      "image": "https://www.mutapatimes.com/img/cards/news/a6976dd5c533.png",
      "pubDate": "2026-05-12T22:03:49+00:00",
      "category": "Health"
    },
    {
      "kind": "news",
      "title": "International Nursing Day: Zimbabwe salutes its nurses",
      "link": "https://mutapatimes.com/news/2026-05-13-international-nursing-day-zimbabwe-salutes-its-nurses-5523e8",
      "image": "https://www.mutapatimes.com/img/cards/news/680067a7993f.png",
      "pubDate": "2026-05-12T22:03:49+00:00",
      "category": "Health"
    },
    {
      "kind": "news",
      "title": "CZI tells private sector to leverage Zim’s trade pacts",
      "link": "https://mutapatimes.com/articles/2026-05-12-czi-tells-private-sector-to-leverage-zims-trade-pacts",
      "image": "https://www.mutapatimes.com/img/cards/news/63afdf5a33b6.png",
      "pubDate": "2026-05-12T22:02:01+00:00",
      "category": "Policy"
    },
    {
      "kind": "economy",
      "title": "Zim goods exports (4Q trailing to 2025 Q4): $10.0B, +10.2% vs prior period.",
      "link": "https://mutapatimes.com/economy?d=2026-05-13",
      "image": "https://mutapatimes.com/img/cards/economy-snapshot.png?v=2026-05-13",
      "pubDate": "2026-05-12T22:00:00+00:00",
      "category": "Economy"
    },
    {
      "kind": "fx",
      "title": "Zim FX snapshot 13 May 2026: 1 USD = 25.76 ZWG · best from UK £100 → $132.19 via Wise",
      "link": "https://mutapatimes.com/fx?d=2026-05-13",
      "image": "https://mutapatimes.com/img/cards/fx-snapshot.png?v=2026-05-13",
      "pubDate": "2026-05-12T22:00:00+00:00",
      "category": "FX"
    },
    {
      "kind": "weather",
      "title": "Zim weather 13 May: Harare overcast · high 27° / low 16°",
      "link": "https://mutapatimes.com/weather?d=2026-05-13",
      "image": "https://mutapatimes.com/img/cards/weather-snapshot.png?v=2026-05-13",
      "pubDate": "2026-05-12T22:00:00+00:00",
      "category": "Weather"
    },
    {
      "kind": "jobs",
      "title": "Social Intern — The Mutapa Times (Remote · 3 days/week · 3 months)",
      "link": "https://mutapatimes.com/jobs#social-intern",
      "image": "https://mutapatimes.com/img/cards/jobs/internship-social-intern.png",
      "pubDate": "2026-05-12T22:00:00+00:00",
      "category": "Internship"
    },
    {
      "kind": "jobs",
      "title": "Editor Intern — The Mutapa Times (Remote · 3 days/week · 3 months)",
      "link": "https://mutapatimes.com/jobs#editor-intern",
      "image": "https://mutapatimes.com/img/cards/jobs/internship-editor-intern.png",
      "pubDate": "2026-05-12T22:00:00+00:00",
      "category": "Internship"
    },
    {
      "kind": "jobs",
      "title": "Data Intern — The Mutapa Times (Remote · 3 days/week · 3 months)",
      "link": "https://mutapatimes.com/jobs#data-intern",
      "image": "https://mutapatimes.com/img/cards/jobs/internship-data-intern.png",
      "pubDate": "2026-05-12T22:00:00+00:00",
      "category": "Internship"
    },
    {
      "kind": "jobs",
      "title": "Marist Brothers High School, Dete — Driver/ Boarding Master",
      "link": "https://vacancymail.co.zw/jobs/driver-boarding-master-67497/",
      "image": "https://mutapatimes.com/img/cards/jobs/be5ecde59ecf.png",
      "pubDate": "2026-05-12T22:00:00+00:00",
      "category": "Jobs"
    },
    {
      "kind": "jobs",
      "title": "Volsec Security — CCTV OPERATORS",
      "link": "https://vacancymail.co.zw/jobs/cctv-operators-67496/",
      "image": "https://mutapatimes.com/img/cards/jobs/4c1043769681.png",
      "pubDate": "2026-05-12T22:00:00+00:00",
      "category": "Jobs"
    },
    {
      "kind": "jobs",
      "title": "Volsec Security — INSPECTOR",
      "link": "https://vacancymail.co.zw/jobs/inspector-67495/",
      "image": "https://mutapatimes.com/img/cards/jobs/842f26c6828d.png",
      "pubDate": "2026-05-12T22:00:00+00:00",
      "category": "Jobs"
    },
    {
      "kind": "jobs",
      "title": "Finance Executive : Hungwe Wire and Rope",
      "link": "https://vacancymail.co.zw/jobs/finance-executive-hungwe-wire-and-rope-67494/",
      "image": "https://mutapatimes.com/img/cards/jobs/122bf0db2e84.png",
      "pubDate": "2026-05-12T22:00:00+00:00",
      "category": "Jobs"
    },
    {
      "kind": "jobs",
      "title": "Zimbabwe Ezekiel Guti University — LECTURER/SENIOR LECTURER/ASSOCIATE PROFESSOR/PROFESSOR (1 POST) FOR BCOM HONOURS IN ACCOUNTING – DEPARTMENT OF ACCOUNTING, FINANCE AND HUMAN CAPITAL MANAGEMENT",
      "link": "https://vacancymail.co.zw/jobs/lecturersenior-lecturerassociate-professorprofessor-1-post-for-bcom-honours-in-accounting-department-of-accounting-finance-and-human-capital-management-67493/",
      "image": "https://mutapatimes.com/img/cards/jobs/c6df904d2592.png",
      "pubDate": "2026-05-12T22:00:00+00:00",
      "category": "Jobs"
    },
    {
      "kind": "jobs",
      "title": "Marist Brothers High School, Dete — 'A' Level FRS & Heritage Teacher",
      "link": "https://vacancymail.co.zw/jobs/a-level-frs-heritage-teacher-67492/",
      "image": "https://mutapatimes.com/img/cards/jobs/3121cdd88066.png",
      "pubDate": "2026-05-12T22:00:00+00:00",
      "category": "Jobs"
    },
    {
      "kind": "jobs",
      "title": "Ixar Mobile ~~ 0 — Electrical Installations Trainer",
      "link": "https://vacancymail.co.zw/jobs/electrical-installations-trainer-67491/",
      "image": "https://mutapatimes.com/img/cards/jobs/0d8ac0581586.png",
      "pubDate": "2026-05-12T22:00:00+00:00",
      "category": "Jobs"
    },
    {
      "kind": "jobs",
      "title": "Marist Brothers High School, Dete — 'A' LEVEL GEOGRAPHY TEACHER",
      "link": "https://vacancymail.co.zw/jobs/a-level-geography-teacher-67490/",
      "image": "https://mutapatimes.com/img/cards/jobs/beba06ceb1ee.png",
      "pubDate": "2026-05-12T22:00:00+00:00",
      "category": "Jobs"
    },
    {
      "kind": "jobs",
      "title": "Veer Freight Private Limited — Freight Forwarding Intern/Clerk",
      "link": "https://vacancymail.co.zw/jobs/freight-forwarding-internclerk-67489/",
      "image": "https://mutapatimes.com/img/cards/jobs/6f17b4dd8630.png",
      "pubDate": "2026-05-12T22:00:00+00:00",
      "category": "Jobs"
    },
    {
      "kind": "jobs",
      "title": "Veer Freight Private Limited — Cargo Handler",
      "link": "https://vacancymail.co.zw/jobs/cargo-handler-67488/",
      "image": "https://mutapatimes.com/img/cards/jobs/97f674bee91a.png",
      "pubDate": "2026-05-12T22:00:00+00:00",
      "category": "Jobs"
    },
    {
      "kind": "property",
      "title": "USD 335,000 — Investment Opportunity With Great Rental Returns (Emerald Hill, Harare West)",
      "link": "https://www.property.co.zw/for-sale/townhouses-jspp236612",
      "image": "https://mutapatimes.com/img/cards/properties/11b52c28713f.png",
      "pubDate": "2026-05-12T22:00:00+00:00",
      "category": "Property"
    }
  ]
}