{
  "fetched_at": "2026-06-28T05:06:26.441886+00:00",
  "source": "https://open.er-api.com/v6/latest/USD",
  "source_label": "open.er-api.com (official interbank composite)",
  "base": "USD",
  "as_of": "Sun, 28 Jun 2026 00:02:31 +0000",
  "next_update": "Mon, 29 Jun 2026 00:11:41 +0000",
  "rates": {
    "ZWG": 26.8272,
    "ZAR": 16.462521,
    "BWP": 14.015667,
    "MZN": 63.54323,
    "ZMW": 18.060921,
    "GBP": 0.757419,
    "EUR": 0.878019,
    "AUD": 1.449499,
    "CAD": 1.418719,
    "CNY": 6.81116,
    "AED": 3.6725,
    "USD": 1.0
  },
  "hero": "ZWG",
  "hero_label": "Zim Gold &middot; Reserve Bank of Zimbabwe official rate (composite)",
  "hero_name": "Zim Gold",
  "converter_order": [
    "USD",
    "ZWG",
    "GBP",
    "ZAR",
    "EUR",
    "BWP"
  ]
}