{
  "fetched_at": "2026-05-20T17:42:24.992521+00:00",
  "source": "https://open.er-api.com/v6/latest/USD",
  "source_label": "open.er-api.com (official interbank composite)",
  "base": "USD",
  "as_of": "Wed, 20 May 2026 00:02:31 +0000",
  "next_update": "Thu, 21 May 2026 00:27:41 +0000",
  "rates": {
    "ZWG": 26.082,
    "ZAR": 16.689768,
    "BWP": 13.849052,
    "MZN": 63.544354,
    "ZMW": 18.91819,
    "GBP": 0.746281,
    "EUR": 0.861198,
    "AUD": 1.406183,
    "CAD": 1.374935,
    "CNY": 6.820724,
    "AED": 3.6725,
    "USD": 1.0
  }
}