{
  "fetched_at": "2026-05-11T15:00:25.441063+00:00",
  "sources": [
    "vacancymail.co.zw"
  ],
  "count": 10,
  "jobs": [
    {
      "title": "Driver Instructor",
      "url": "https://vacancymail.co.zw/jobs/driver-instructor-67452/",
      "company": "National Foods Holdings Limited",
      "logo": "https://vacancymail.co.zw/media/logo_national-foods-holdings-limited_123028.png",
      "summary": "Applications are invited from suitably qualified and experienced persons to fill the above position, which nas arisen in National Foods Limited (Distribution Division). Safety is our licence to opera…",
      "location": "Harare",
      "expires": "14 May 2026",
      "type": "Full Time",
      "salary": "",
      "posted": "50 minutes",
      "source": "vacancymail.co.zw"
    },
    {
      "title": "Electronic Engineer",
      "url": "https://vacancymail.co.zw/jobs/electronic-engineer-67451/",
      "company": "InstaToll Zimbabwe (Pty) Ltd",
      "logo": "https://vacancymail.co.zw/media/logo/logo_instatoll-zimbabwe-pty-ltd_M.png",
      "summary": "Start Date: June 2026 Reporting Manager : Electronic Engineer Senior Software Engineer /Technical Manager",
      "location": "Harare",
      "expires": "13 May 2026",
      "type": "Full Time",
      "salary": "",
      "posted": "52 minutes",
      "source": "vacancymail.co.zw"
    },
    {
      "title": "Plant Manager - Metallurgical Operations",
      "url": "https://vacancymail.co.zw/jobs/plant-manager-metallurgical-operations-67450/",
      "company": "Croco Holdings",
      "logo": "https://vacancymail.co.zw/media/logo/logo_croco-holdings_T.png",
      "summary": "PLANT MANAGER - METALLURGICAL OPERATIONS Applications are invited from interested and suitably qualified persons to fill in the following vacancy that has arisen within Croco Holdings group. Role Ove…",
      "location": "Harare",
      "expires": "12 May 2026",
      "type": "Full Time",
      "salary": "",
      "posted": "1 hour",
      "source": "vacancymail.co.zw"
    },
    {
      "title": "Sales and Marketing Officer",
      "url": "https://vacancymail.co.zw/jobs/sales-and-marketing-officer-67449/",
      "company": "",
      "logo": "https://vacancymail.co.zw/static/vacancymail.co.za.png",
      "summary": "A growing burial supplies establishment based in Bulawayo is seeking to recruit a suitably qualified, self-motivated, and results-oriented individual to join our team in the following position: Sales…",
      "location": "Bulawayo",
      "expires": "14 May 2026",
      "type": "Full Time",
      "salary": "",
      "posted": "1 hour, 8 minutes",
      "source": "vacancymail.co.zw"
    },
    {
      "title": "Storage Tank Operator",
      "url": "https://vacancymail.co.zw/jobs/storage-tank-operator-67448/",
      "company": "Green Fuel",
      "logo": "https://vacancymail.co.zw/media/logo/logo_green-fuelq.png",
      "summary": "Despatch Tank Operator takes ethanol storage tanks stock daily and loads the road tankers with ordered ethanol volumes according to the marketing requirements.",
      "location": "Chipinge",
      "expires": "15 May 2026",
      "type": "Full Time",
      "salary": "",
      "posted": "1 hour, 39 minutes",
      "source": "vacancymail.co.zw"
    },
    {
      "title": "Carpenter",
      "url": "https://vacancymail.co.zw/jobs/carpenter-67447/",
      "company": "Green Fuel",
      "logo": "https://vacancymail.co.zw/media/logo/logo_green-fuelq.png",
      "summary": "BigFive Carpenter Position Summary of Carpenter Duties The Camp Carpenter is responsible for maintaining, repairing, and constructing all wooden structures, furniture, and fittings throughout the saf…",
      "location": "Mbire",
      "expires": "15 May 2026",
      "type": "Full Time",
      "salary": "",
      "posted": "1 hour, 52 minutes",
      "source": "vacancymail.co.zw"
    },
    {
      "title": "Independent Sales Executive",
      "url": "https://vacancymail.co.zw/jobs/independent-sales-executive-67446/",
      "company": "Lightguard Security",
      "logo": "https://vacancymail.co.zw/static/vacancymail.co.zw.png",
      "summary": "LightGuard Security is inviting applications from ambitious, well-connected, and results-driven individuals to join our growing team as an Independent Sales Executives / Business Development Agent.Th…",
      "location": "Harare",
      "expires": "14 May 2026",
      "type": "Full Time",
      "salary": "",
      "posted": "1 hour, 57 minutes",
      "source": "vacancymail.co.zw"
    },
    {
      "title": "Accountant",
      "url": "https://vacancymail.co.zw/jobs/accountant-67445/",
      "company": "",
      "logo": "https://vacancymail.co.zw/static/vacancymail.co.za.png",
      "summary": "Elyon Healthcare (UK) | Remote (Zimbabwe-Based) | Full-Time Role Overview Elyon Healthcare , a UK-based private, independent care provider and property company is seeking a detail-oriented, proactive…",
      "location": "Harare",
      "expires": "01 Jun 2026",
      "type": "Full Time",
      "salary": "",
      "posted": "2 hours, 37 minutes",
      "source": "vacancymail.co.zw"
    },
    {
      "title": "Accountant",
      "url": "https://vacancymail.co.zw/jobs/accountant-67444/",
      "company": "",
      "logo": "https://vacancymail.co.zw/static/vacancymail.co.za.png",
      "summary": "*PlanForSixty MFI is Recruiting* **Position:** Accountant **Reports to:** General Manager **Location:** Zimbabwe **Team Size:** 3 (including this role) About the Company We are a small but growing mi…",
      "location": "Harare",
      "expires": "15 May 2026",
      "type": "Full Time",
      "salary": "",
      "posted": "7 hours, 33 minutes",
      "source": "vacancymail.co.zw"
    },
    {
      "title": "2026-2028 Graduate Trainee Programme",
      "url": "https://vacancymail.co.zw/jobs/2026-2028-graduate-trainee-programme-67443/",
      "company": "RBZ - Reserve Bank Of Zimbabwe",
      "logo": "https://vacancymail.co.zw/media/logo_reserve-bank-of-zimbabwe_82430.png",
      "summary": "The Reserve Bank of Zimbabwe (RBZ) invites applications from highly motivated, analytical, and results-oriented graduates to join its 2026-2028 Graduate Trainee Programme. This two-year programme is…",
      "location": "Harare",
      "expires": "12 May 2026",
      "type": "Full Time",
      "salary": "",
      "posted": "1 day, 2 hours",
      "source": "vacancymail.co.zw"
    }
  ]
}