{
  "fetched_at": "2026-05-22T04:35:27.826990+00:00",
  "source": "https://www.property.co.zw/houses-for-sale",
  "count": 22,
  "listings": [
    {
      "title": "Neat & Versatile 3-Bedroom Home in Suburbs",
      "url": "https://www.property.co.zw/for-sale/houses-clrp245985",
      "price": "USD 250,000",
      "location": "Suburbs, Bulawayo East",
      "image": "https://www.property.co.zw/uploadedfiles/03/11/0b/03110b10-4143-4e20-a09b-62f92f042f53_thumbnail591.webp",
      "beds": "3",
      "baths": "2"
    },
    {
      "title": "4BR Marlborough Home on 4000m² — Pool & Garden",
      "url": "https://www.property.co.zw/for-sale/houses-rrt234742",
      "price": "USD 280,000",
      "location": "Marlborough, Harare West",
      "image": "https://www.property.co.zw/uploadedfiles/8c/47/00/8c47007d-f2a0-42b1-81b3-7f8e840e28e2_thumbnail591.webp",
      "beds": "4",
      "baths": "2"
    },
    {
      "title": "Keen Seller!",
      "url": "https://www.property.co.zw/for-sale/houses-rws232983",
      "price": "USD 70,000",
      "location": "Mabvazuva, Ruwa",
      "image": "https://www.property.co.zw/uploadedfiles/f9/98/b9/f998b9a6-d6e1-4bce-bcbc-12249159ec0b_thumbnail591.webp",
      "beds": "4",
      "baths": "3"
    },
    {
      "title": "Exquisite Borrowdale Brooke Property",
      "url": "https://www.property.co.zw/for-sale/houses-sef194379",
      "price": "USD 600,000",
      "location": "Borrowdale Brooke, Harare North",
      "image": "https://www.property.co.zw/uploadedfiles/97/9d/5d/979d5db7-1538-41f4-b742-778973043328_thumbnail591.webp",
      "beds": "8",
      "baths": "10"
    },
    {
      "title": "Prime Investment || Airport road, Hatfield",
      "url": "https://www.property.co.zw/for-sale/houses-rws243492",
      "price": "USD 550,000",
      "location": "Hatfield, Harare South",
      "image": "https://www.property.co.zw/uploadedfiles/51/f9/ec/51f9ec02-2e9a-4e25-849f-db4bd7006aa3_thumbnail591.webp",
      "beds": "4",
      "baths": "2"
    },
    {
      "title": "Beautiful Family Home",
      "url": "https://www.property.co.zw/for-sale/houses-sby247456",
      "price": "USD 110,000",
      "location": "Zimre Park, Harare East",
      "image": "https://www.property.co.zw/uploadedfiles/94/2c/af/942cafa9-ba9b-477c-b368-edccf9e25388_thumbnail591.webp",
      "beds": "5",
      "baths": ""
    },
    {
      "title": "Modern 3-bedroom townhouses in Hillside!",
      "url": "https://www.property.co.zw/for-sale/townhouses-red245474",
      "price": "USD 220,000",
      "location": "Hillside, Bulawayo South",
      "image": "https://www.property.co.zw/uploadedfiles/d6/86/08/d6860841-9279-44dc-9d2e-5070a983c78e_thumbnail591.webp",
      "beds": "3",
      "baths": "3"
    },
    {
      "title": "Superb opportunity in Gweru",
      "url": "https://www.property.co.zw/for-sale/houses-rws247047",
      "price": "USD 140,000",
      "location": "Adelaide Park, Gweru",
      "image": "https://www.property.co.zw/uploadedfiles/2b/dd/69/2bdd69e4-ada7-432a-84ed-1bec7022551a_thumbnail591.webp",
      "beds": "5",
      "baths": "4"
    },
    {
      "title": "Family Home in Borrowdale Brooke Estate",
      "url": "https://www.property.co.zw/for-sale/houses-mtx241861",
      "price": "USD 700,000",
      "location": "Borrowdale Brooke, Harare North",
      "image": "https://www.property.co.zw/uploadedfiles/4a/73/3c/4a733c5c-d0c1-4a19-ac09-094129ddef89_thumbnail591.webp",
      "beds": "4",
      "baths": "3"
    },
    {
      "title": "Title Deeds Ready | Southview Park House For Sale",
      "url": "https://www.property.co.zw/for-sale/houses-leg246757",
      "price": "USD 75,000",
      "location": "Southview Park, Harare South",
      "image": "https://www.property.co.zw/uploadedfiles/27/3a/74/273a748d-33c1-47fc-9bef-5288101c9b06_thumbnail591.webp",
      "beds": "3",
      "baths": "2"
    },
    {
      "title": "Leafy 3 Bed Victoria Falls Home with Flatlet & Garden Verandah",
      "url": "https://www.property.co.zw/for-sale/houses-jspp238355",
      "price": "USD 350,000",
      "location": "Victoria Falls",
      "image": "https://www.property.co.zw/uploadedfiles/75/14/05/7514052c-af12-4f87-a287-40127f243fec_thumbnail591.webp",
      "beds": "6",
      "baths": "3"
    },
    {
      "title": "Your Dream Getaway Awaits In Kariba – 3 Properties",
      "url": "https://www.property.co.zw/for-sale/houses-clrp182676",
      "price": "USD 395,000",
      "location": "Wild Heritage Lodge, Kariba",
      "image": "https://www.property.co.zw/uploadedfiles/9d/86/ab/9d86ab07-60ff-4d91-a244-bad1b0b7c408_thumbnail591.webp",
      "beds": "3",
      "baths": "3"
    },
    {
      "title": "New Gated Community , Quinnington Harare North",
      "url": "https://www.property.co.zw/for-sale/houses-hos245016",
      "price": "USD 375,000",
      "location": "Quinnington, Harare North",
      "image": "https://www.property.co.zw/uploadedfiles/54/36/41/54364197-63ba-477c-9863-0145af6b4a42_thumbnail591.webp",
      "beds": "4",
      "baths": "3"
    },
    {
      "title": "5 Bedroom Signature Residence in Helensvale",
      "url": "https://www.property.co.zw/for-sale/houses-mtx241891",
      "price": "USD 640,000",
      "location": "Helensvale, Harare North",
      "image": "https://www.property.co.zw/uploadedfiles/dc/ad/87/dcad87f9-9781-4a35-ba30-8c1b149538df_thumbnail591.webp",
      "beds": "5",
      "baths": "5"
    },
    {
      "title": "Exquisite Hogerty Hill Family Home: Modern Luxury with Breathtaking Views",
      "url": "https://www.property.co.zw/for-sale/houses-sef231739",
      "price": "USD 470,000",
      "location": "Hogerty Hill, Harare North",
      "image": "https://www.property.co.zw/uploadedfiles/9f/28/33/9f2833c1-01aa-4c8a-a0a6-33f82879c442_thumbnail591.webp",
      "beds": "6",
      "baths": "6"
    },
    {
      "title": "A Spacious Family Home",
      "url": "https://www.property.co.zw/for-sale/houses-pgp244926",
      "price": "USD 250,000",
      "location": "Burnside, Bulawayo East",
      "image": "https://www.property.co.zw/uploadedfiles/75/02/f4/7502f45d-dbcb-444a-81fa-dc31926673f3_thumbnail591.webp",
      "beds": "4",
      "baths": "2"
    },
    {
      "title": "Eastlea House Reduced For A Quick Sale!!",
      "url": "https://www.property.co.zw/for-sale/houses-rws223352",
      "price": "USD 320,000",
      "location": "Eastlea, Harare East",
      "image": "https://www.property.co.zw/uploadedfiles/d6/b6/fa/d6b6fac9-31cf-4494-bca0-d3ce1870ada5_thumbnail591.webp",
      "beds": "5",
      "baths": "2"
    },
    {
      "title": "Family Sanctuary On Over An Acre",
      "url": "https://www.property.co.zw/for-sale/houses-prl242963",
      "price": "USD 365,000",
      "location": "Mandara, Harare East",
      "image": "https://www.property.co.zw/uploadedfiles/44/de/8a/44de8a2b-5674-4483-a6e7-70676aa948ee_thumbnail591.webp",
      "beds": "3",
      "baths": "2"
    },
    {
      "title": "House for Sale in Southview Park!",
      "url": "https://www.property.co.zw/for-sale/houses-sef245075",
      "price": "USD 75,000",
      "location": "Southview Park, Harare South",
      "image": "https://www.property.co.zw/uploadedfiles/1f/02/f9/1f02f975-299f-41fb-9b8f-328201f99fc9_thumbnail591.webp",
      "beds": "4",
      "baths": "2"
    },
    {
      "title": "A Prestigious Family Home in Ryelands",
      "url": "https://www.property.co.zw/for-sale/houses-knp226759",
      "price": "USD 825,000",
      "location": "Borrowdale, Harare North",
      "image": "https://www.property.co.zw/uploadedfiles/c1/61/89/c161895c-792d-46ba-bc90-da6f73cf0a35_thumbnail591.webp",
      "beds": "5",
      "baths": "4"
    },
    {
      "title": "Secure Lock Up And Go",
      "url": "https://www.property.co.zw/for-sale/townhouses-pgp224886",
      "price": "USD 220,000",
      "location": "Borrowdale West, Harare North",
      "image": "https://www.property.co.zw/uploadedfiles/89/56/b6/8956b650-0465-4cb4-aba1-089411c0e699_thumbnail591.webp",
      "beds": "3",
      "baths": "2"
    },
    {
      "title": "Living in style",
      "url": "https://www.property.co.zw/for-sale/houses-rws242467",
      "price": "USD 550,000",
      "location": "Glen Lorne, Harare North",
      "image": "https://www.property.co.zw/uploadedfiles/fa/db/f7/fadbf7d5-6cf5-4eb4-abb4-68e682c37a6d_thumbnail591.webp",
      "beds": "4",
      "baths": "3"
    }
  ]
}