{
  "fetched_at": "2026-06-16T21:18:40.878779+00:00",
  "source": "https://www.property.co.zw/houses-for-sale",
  "count": 22,
  "listings": [
    {
      "title": "Goodhope Incomplete house for sale at 85%!",
      "url": "https://www.property.co.zw/for-sale/houses-pbox249411",
      "price": "USD 150,000",
      "location": "Goodhope, Harare West",
      "image": "https://www.property.co.zw/uploadedfiles/56/af/06/56af06b2-72ee-4981-8d2f-5a51fe8c5edc_thumbnail591.webp",
      "beds": "4",
      "baths": "3"
    },
    {
      "title": "6 Bedroom House for Sale in Helensvale",
      "url": "https://www.property.co.zw/for-sale/houses-vepr242000",
      "price": "USD 600,000",
      "location": "Borrowdale, Harare North",
      "image": "https://www.property.co.zw/uploadedfiles/a8/dd/ff/a8ddff58-c911-4dcc-8c89-1d86198676e9_thumbnail591.webp",
      "beds": "6",
      "baths": "6"
    },
    {
      "title": "House for sale",
      "url": "https://www.property.co.zw/for-sale/houses-xds235519",
      "price": "USD 140,000",
      "location": "Mainway Meadows, Harare South",
      "image": "https://www.property.co.zw/uploadedfiles/ba/ee/52/baee52fd-9089-41dd-ac2f-58717ce1f73b_thumbnail591.webp",
      "beds": "4",
      "baths": "2"
    },
    {
      "title": "5-Bedroom Home with Borehole in Crowhill Views, Harare North",
      "url": "https://www.property.co.zw/for-sale/houses-hvn188217",
      "price": "USD 130,000",
      "location": "Crowhill Views, Harare North",
      "image": "https://www.property.co.zw/uploadedfiles/5a/ef/24/5aef24ea-8e13-4313-99fb-3b8a022b7d63_thumbnail591.webp",
      "beds": "5",
      "baths": "4"
    },
    {
      "title": "Prime Location. Potential For Commercial",
      "url": "https://www.property.co.zw/for-sale/houses-knp177539",
      "price": "USD 800,000",
      "location": "Harare Drive, Pomona, Harare North",
      "image": "https://www.property.co.zw/uploadedfiles/5b/07/b1/5b07b195-033c-4cba-81fd-878e3ab99025_thumbnail591.webp",
      "beds": "7",
      "baths": "6"
    },
    {
      "title": "Greystone Park – Prime 4,523sqm Property For sale",
      "url": "https://www.property.co.zw/for-sale/houses-pgp238347",
      "price": "USD 550,000",
      "location": "Greystone Park, Harare North",
      "image": "https://www.property.co.zw/uploadedfiles/cd/f5/92/cdf592ae-855b-43d4-b761-92ccf29d11f5_thumbnail591.webp",
      "beds": "4",
      "baths": "2"
    },
    {
      "title": "Luxury Glen Lorne House for Sale – 5 Bedrooms, Spa, Solar, Borehole & 7,000 sqm Stand",
      "url": "https://www.property.co.zw/for-sale/houses-gat238005",
      "price": "USD 600,000",
      "location": "Glen Lorne, Harare North",
      "image": "https://www.property.co.zw/uploadedfiles/57/30/73/57307351-5bc1-4abd-8307-06b7a6268f93_thumbnail591.webp",
      "beds": "5",
      "baths": ""
    },
    {
      "title": "A Reduced Price for your own lake shore proprety on Gletwyn Dam",
      "url": "https://www.property.co.zw/for-sale/houses-knp238492",
      "price": "USD 965,000",
      "location": "Gletwin Park, Harare North",
      "image": "https://www.property.co.zw/uploadedfiles/c8/a2/ce/c8a2ceae-0088-4e52-902c-f35b75b1de76_thumbnail591.webp",
      "beds": "5",
      "baths": "4"
    },
    {
      "title": "Zengeza 4 Extension - Six Bedroom House for Sale",
      "url": "https://www.property.co.zw/for-sale/houses-gat245503",
      "price": "USD 35,000",
      "location": "Zengeza, Chitungwiza",
      "image": "https://www.property.co.zw/uploadedfiles/a4/25/ff/a425ff42-8b8a-4e8e-a5a9-8f7aefeb7f7f_thumbnail591.webp",
      "beds": "6",
      "baths": "2"
    },
    {
      "title": "Entertainers Dream",
      "url": "https://www.property.co.zw/for-sale/houses-psp241191",
      "price": "USD 4,500,000",
      "location": "Quinnington, Harare North",
      "image": "https://www.property.co.zw/uploadedfiles/80/c9/9c/80c99c61-df58-4c81-97af-166660ce533e_thumbnail591.webp",
      "beds": "9",
      "baths": "6"
    },
    {
      "title": "Mount Pleasant heights 4-bed house for sale.",
      "url": "https://www.property.co.zw/for-sale/houses-hos235830",
      "price": "USD 285,000",
      "location": "Mount Pleasant Heights, Harare North",
      "image": "https://www.property.co.zw/uploadedfiles/92/fb/0e/92fb0ebf-5485-4d4e-906b-de9c11295012_thumbnail591.webp",
      "beds": "4",
      "baths": "3"
    },
    {
      "title": "Brand New Complex - Secure - Neat",
      "url": "https://www.property.co.zw/for-sale/townhouses-apc248838",
      "price": "USD 370,000",
      "location": "Newlands, Harare North",
      "image": "https://www.property.co.zw/uploadedfiles/5a/48/be/5a48beed-81cd-4d49-92b5-ca834ccaee4d_thumbnail591.webp",
      "beds": "3",
      "baths": "2"
    },
    {
      "title": "Great Investment Opportunity",
      "url": "https://www.property.co.zw/for-sale/townhouses-jspp235653",
      "price": "USD 845,000",
      "location": "Mount Pleasant, Harare North",
      "image": "https://www.property.co.zw/uploadedfiles/a3/be/59/a3be59ec-b8a2-470d-8cd5-0fc9e0fcd2bd_thumbnail591.webp",
      "beds": "10",
      "baths": ""
    },
    {
      "title": "3 Bedroom House for Sale in Avenues Mutare",
      "url": "https://www.property.co.zw/for-sale/houses-bnjr248890",
      "price": "USD 150,000",
      "location": "Avenues, Mutare",
      "image": "https://www.property.co.zw/uploadedfiles/48/75/70/4875709e-e433-484d-aa0e-a03595b51d7e_thumbnail591.webp",
      "beds": "3",
      "baths": "1"
    },
    {
      "title": "AVONDALE Executive Family Home | US$570k",
      "url": "https://www.property.co.zw/for-sale/houses-kha248308",
      "price": "USD 570,000",
      "location": "Avondale, Harare North",
      "image": "https://www.property.co.zw/uploadedfiles/e2/c4/3f/e2c43f7c-1b62-4941-b542-a27b034ce7fb_thumbnail591.webp",
      "beds": "4",
      "baths": "3"
    },
    {
      "title": "Arlington 4-Bed Townhouse Complex ,Borehole, Solar & 24hr Security",
      "url": "https://www.property.co.zw/for-sale/townhouses-cami249353",
      "price": "USD 165,000",
      "location": "Arlington, Harare South",
      "image": "https://www.property.co.zw/uploadedfiles/4b/73/22/4b73224b-06eb-4115-b4db-6baa58368a88_thumbnail591.webp",
      "beds": "4",
      "baths": "3"
    },
    {
      "title": "Spacious Pomona 5-Bed Home In Borrowdale Pomona",
      "url": "https://www.property.co.zw/for-sale/houses-sef244687",
      "price": "USD 350,000",
      "location": "Pomona, Harare North",
      "image": "https://www.property.co.zw/uploadedfiles/91/4c/8a/914c8ab1-3e3f-40ca-80c2-824dfd8d8796_thumbnail591.webp",
      "beds": "5",
      "baths": "4"
    },
    {
      "title": "Glenorah House For Sale",
      "url": "https://www.property.co.zw/for-sale/houses-pex235553",
      "price": "USD 55,000",
      "location": "Glen Norah, Harare High Density",
      "image": "https://www.property.co.zw/uploadedfiles/59/25/64/59256439-92c0-4e39-90d3-7ab6dfe2a550_thumbnail591.webp",
      "beds": "4",
      "baths": "1"
    },
    {
      "title": "Modern 3-bedroom townhouses in Hillside!",
      "url": "https://www.property.co.zw/for-sale/townhouses-red245474",
      "price": "USD 220,000",
      "location": "Hillside, Bulawayo South",
      "image": "https://www.property.co.zw/uploadedfiles/d6/86/08/d6860841-9279-44dc-9d2e-5070a983c78e_thumbnail591.webp",
      "beds": "3",
      "baths": "3"
    },
    {
      "title": "Exceptional Family Estate On Nearly 4 Acres",
      "url": "https://www.property.co.zw/for-sale/houses-prl235469",
      "price": "USD 1,100,000",
      "location": "Helensvale, Harare North",
      "image": "https://www.property.co.zw/uploadedfiles/e4/d9/0f/e4d90fd6-36cb-442e-8583-9025798963cd_thumbnail591.webp",
      "beds": "5",
      "baths": "5"
    },
    {
      "title": "Investment opportunity",
      "url": "https://www.property.co.zw/for-sale/houses-rws243015",
      "price": "USD 70,000",
      "location": "Zimre Park, Harare East",
      "image": "https://www.property.co.zw/uploadedfiles/7a/17/85/7a1785de-cb56-4a04-9ac1-81e271ae3f6e_thumbnail591.webp",
      "beds": "3",
      "baths": "1"
    },
    {
      "title": "Elegant two-storey 5-Bed Borrowdale Home",
      "url": "https://www.property.co.zw/for-sale/houses-lcre242974",
      "price": "USD 450,000",
      "location": "Borrowdale, Harare North",
      "image": "https://www.property.co.zw/uploadedfiles/6e/81/87/6e81875d-a0f0-40b5-b21b-7cd20e2e7656_thumbnail591.webp",
      "beds": "5",
      "baths": "4"
    }
  ]
}