{
  "fetched_at": "2026-05-12T07:22:44.427914+00:00",
  "source": "https://open-meteo.com/",
  "tz": "Africa/Harare",
  "cities": [
    {
      "city": "Harare",
      "current_temp": 22.4,
      "high": 26.2,
      "low": 16.4,
      "precip_mm": 0.0,
      "precip_prob": 0,
      "humidity": 49,
      "wind_kmh": 10.6,
      "code": 3,
      "label": "Overcast",
      "emoji": "☁️"
    },
    {
      "city": "Bulawayo",
      "current_temp": 22.0,
      "high": 27.6,
      "low": 14.2,
      "precip_mm": 0.0,
      "precip_prob": 0,
      "humidity": 23,
      "wind_kmh": 8.4,
      "code": 0,
      "label": "Clear sky",
      "emoji": "☀️"
    },
    {
      "city": "Mutare",
      "current_temp": 23.8,
      "high": 27.5,
      "low": 15.1,
      "precip_mm": 0.0,
      "precip_prob": 0,
      "humidity": 56,
      "wind_kmh": 0.8,
      "code": 3,
      "label": "Overcast",
      "emoji": "☁️"
    },
    {
      "city": "Gweru",
      "current_temp": 22.6,
      "high": 27.0,
      "low": 15.4,
      "precip_mm": 0.0,
      "precip_prob": 0,
      "humidity": 39,
      "wind_kmh": 7.9,
      "code": 0,
      "label": "Clear sky",
      "emoji": "☀️"
    },
    {
      "city": "Masvingo",
      "current_temp": 22.5,
      "high": 28.2,
      "low": 13.4,
      "precip_mm": 0.0,
      "precip_prob": 0,
      "humidity": 52,
      "wind_kmh": 2.2,
      "code": 0,
      "label": "Clear sky",
      "emoji": "☀️"
    },
    {
      "city": "Victoria Falls",
      "current_temp": 22.4,
      "high": 31.0,
      "low": 14.1,
      "precip_mm": 0.0,
      "precip_prob": 0,
      "humidity": 30,
      "wind_kmh": 5.0,
      "code": 0,
      "label": "Clear sky",
      "emoji": "☀️"
    }
  ]
}