{
  "fetched_at": "2026-07-14T22:13:20.670883+00:00",
  "source": "https://open-meteo.com/",
  "tz": "Africa/Johannesburg",
  "cities": [
    {
      "city": "Johannesburg",
      "current_temp": 11.4,
      "high": 19.6,
      "low": 8.7,
      "precip_mm": 0.0,
      "precip_prob": 0,
      "humidity": 51,
      "wind_kmh": 7.7,
      "code": 0,
      "label": "Clear sky",
      "emoji": "☀️"
    },
    {
      "city": "Cape Town",
      "current_temp": 10.4,
      "high": 16.7,
      "low": 10.1,
      "precip_mm": 0.3,
      "precip_prob": 6,
      "humidity": 98,
      "wind_kmh": 5.8,
      "code": 51,
      "label": "Light drizzle",
      "emoji": "🌦️"
    },
    {
      "city": "Durban",
      "current_temp": 15.3,
      "high": 22.2,
      "low": 11.3,
      "precip_mm": 0.0,
      "precip_prob": 0,
      "humidity": 92,
      "wind_kmh": 6.4,
      "code": 2,
      "label": "Partly cloudy",
      "emoji": "⛅"
    },
    {
      "city": "Pretoria",
      "current_temp": 12.7,
      "high": 22.9,
      "low": 10.9,
      "precip_mm": 0.0,
      "precip_prob": 0,
      "humidity": 52,
      "wind_kmh": 7.9,
      "code": 0,
      "label": "Clear sky",
      "emoji": "☀️"
    },
    {
      "city": "Gqeberha",
      "current_temp": 14.0,
      "high": 18.6,
      "low": 13.0,
      "precip_mm": 0.0,
      "precip_prob": 2,
      "humidity": 84,
      "wind_kmh": 12.5,
      "code": 3,
      "label": "Overcast",
      "emoji": "☁️"
    },
    {
      "city": "Bloemfontein",
      "current_temp": 8.9,
      "high": 17.8,
      "low": 7.4,
      "precip_mm": 0.0,
      "precip_prob": 0,
      "humidity": 43,
      "wind_kmh": 0.8,
      "code": 3,
      "label": "Overcast",
      "emoji": "☁️"
    }
  ]
}